term_symbols/__init__.py
term_symbols/terms.py
term_symbols-0.1.4.dist-info/METADATA
term_symbols-0.1.4.dist-info/WHEEL
term_symbols-0.1.4.dist-info/entry_points.txt
term_symbols-0.1.4.dist-info/licenses/LICENSE
term_symbols-0.1.4.dist-info/RECORD
