Metadata-Version: 2.4
Name: term-symbols
Version: 0.1.4
Summary: A Python package for calculating atomic term symbols from electron configurations
Project-URL: Homepage, https://ccheung93.github.io/notes/term_symbols/
Project-URL: Repository, https://github.com/ccheung93/atomic-term-symbol-calculator
Project-URL: Bug Tracker, https://github.com/ccheung93/atomic-term-symbol-calculator/issues
Project-URL: Documentation, https://ccheung93.github.io/notes/term_symbols/
Author-email: Charles Cheung <ccheung@udel.edu>
License: MIT
License-File: LICENSE
Keywords: atomic-physics,chemistry,electron-configuration,quantum-mechanics,term-symbols
Classifier: Development Status :: 4 - Beta
Classifier: Intended Audience :: Education
Classifier: Intended Audience :: Science/Research
Classifier: License :: OSI Approved :: MIT License
Classifier: Operating System :: OS Independent
Classifier: Programming Language :: Python :: 3
Classifier: Programming Language :: Python :: 3.8
Classifier: Programming Language :: Python :: 3.9
Classifier: Programming Language :: Python :: 3.10
Classifier: Programming Language :: Python :: 3.11
Classifier: Programming Language :: Python :: 3.12
Classifier: Topic :: Education
Classifier: Topic :: Scientific/Engineering :: Chemistry
Classifier: Topic :: Scientific/Engineering :: Physics
Requires-Python: >=3.8
Requires-Dist: numpy
Requires-Dist: pandas
Provides-Extra: test
Requires-Dist: pytest; extra == 'test'
